django_structlog_duration/__init__.py
django_structlog_duration/middleware.py
django_structlog_duration-0.0.1.dist-info/LICENSE
django_structlog_duration-0.0.1.dist-info/METADATA
django_structlog_duration-0.0.1.dist-info/WHEEL
django_structlog_duration-0.0.1.dist-info/RECORD
